amundsen_gremlin/__init__.py
amundsen_gremlin/config.py
amundsen_gremlin/gremlin_model.py
amundsen_gremlin/gremlin_shared.py
amundsen_gremlin/py.typed
amundsen_gremlin/script_translator.py
amundsen_gremlin/test_and_development_shard.py
amundsen_gremlin/neptune_bulk_loader/__init__.py
amundsen_gremlin/neptune_bulk_loader/api.py
amundsen_gremlin/neptune_bulk_loader/gremlin_model_converter.py
amundsen_gremlin/utils/__init__.py
amundsen_gremlin/utils/streams.py
for_requests/__init__.py
for_requests/assume_role_aws4auth.py
for_requests/aws4auth_compatible.py
for_requests/host_header_ssl.py
neptune_python_utils/__init__.py
neptune_python_utils/bulkload.py
neptune_python_utils/endpoints.py
neptune_python_utils/glue_gremlin_client.py
neptune_python_utils/glue_gremlin_csv_transforms.py
neptune_python_utils/glue_neptune_connection_info.py
neptune_python_utils/gremlin_utils.py
neptune_python_utils/streams.py
ssl_override_server_hostname/__init__.py
ssl_override_server_hostname/ssl_context.py
amundsen_gremlin-0.0.13.dist-info/LICENSE
amundsen_gremlin-0.0.13.dist-info/METADATA
amundsen_gremlin-0.0.13.dist-info/WHEEL
amundsen_gremlin-0.0.13.dist-info/top_level.txt
amundsen_gremlin-0.0.13.dist-info/RECORD
