Metadata-Version: 2.1
Name: amundsen-gremlin
Version: 0.0.13
Summary: Gremlin code library for Amundsen
Home-page: https://github.com/amundsen-io/amundsengremlin
Maintainer: Amundsen TSC
Maintainer-email: amundsen-tsc@lists.lfai.foundation
License: UNKNOWN
Platform: UNKNOWN
Classifier: Programming Language :: Python :: 3.6
Classifier: Programming Language :: Python :: 3.7
Requires-Python: >=3.6
